setup.cfg
setup.py
Lawpypi/Binomialdistribution.py
Lawpypi/Gaussiandistribution.py
Lawpypi/Generaldistribution.py
Lawpypi/__init__.py
Lawpypi.egg-info/PKG-INFO
Lawpypi.egg-info/SOURCES.txt
Lawpypi.egg-info/dependency_links.txt
Lawpypi.egg-info/not-zip-safe
Lawpypi.egg-info/top_level.txt